smv/__init__.py
smv/cli.py
smv/config.py
smv/core.py
smv/analyzers/__init__.py
smv/analyzers/image_analyzer.py
smv/analyzers/text_analyzer.py
smv/utils/__init__.py
smv/utils/command_utils.py
smv/utils/file_utils.py
smv/utils/llm_utils.py
smart_mv-0.1.1.dist-info/LICENSE
smart_mv-0.1.1.dist-info/METADATA
smart_mv-0.1.1.dist-info/WHEEL
smart_mv-0.1.1.dist-info/entry_points.txt
smart_mv-0.1.1.dist-info/top_level.txt
smart_mv-0.1.1.dist-info/RECORD
