Metadata-Version: 2.1
Name: smart-mv
Version: 0.1.1
Summary: Smart Move (smv) - AI-powered file organization tool
Author-email: Karis Zhuang <xupingz613@gmail.com>
License: GNU GENERAL PUBLIC LICENSE
Classifier: Programming Language :: Python :: 3
Classifier: License :: OSI Approved :: GNU General Public License v3 (GPLv3)
Classifier: Operating System :: OS Independent
Requires-Python: >=3.8
License-File: LICENSE
Requires-Dist: openai>=1.0.0
Requires-Dist: pypdf>=3.0.0
Requires-Dist: pdf2image>=1.16.0
Requires-Dist: pillow>=9.0.0
